bigdl/__init__.py
bigdl/dllib/__init__.py
bigdl/dllib/nncontext.py
bigdl/dllib/version.py
bigdl/dllib/contrib/__init__.py
bigdl/dllib/contrib/onnx/__init__.py
bigdl/dllib/contrib/onnx/converter_utils.py
bigdl/dllib/contrib/onnx/onnx_loader.py
bigdl/dllib/contrib/onnx/ops_converter.py
bigdl/dllib/contrib/onnx/ops_mapping.py
bigdl/dllib/estimator/__init__.py
bigdl/dllib/estimator/estimator.py
bigdl/dllib/feature/common.py
bigdl/dllib/feature/dataset/__init__.py
bigdl/dllib/feature/dataset/base.py
bigdl/dllib/feature/dataset/dataset.py
bigdl/dllib/feature/dataset/mnist.py
bigdl/dllib/feature/dataset/movielens.py
bigdl/dllib/feature/dataset/news20.py
bigdl/dllib/feature/dataset/sentence.py
bigdl/dllib/feature/dataset/transformer.py
bigdl/dllib/feature/image/__init__.py
bigdl/dllib/feature/image/imagePreprocessing.py
bigdl/dllib/feature/image/imageset.py
bigdl/dllib/feature/image/transforms.py
bigdl/dllib/feature/image3d/__init__.py
bigdl/dllib/feature/image3d/transformation.py
bigdl/dllib/feature/text/__init__.py
bigdl/dllib/feature/text/text_feature.py
bigdl/dllib/feature/text/text_set.py
bigdl/dllib/feature/text/transformer.py
bigdl/dllib/feature/transform/__init__.py
bigdl/dllib/feature/transform/vision/__init__.py
bigdl/dllib/feature/transform/vision/image.py
bigdl/dllib/keras/ToBigDLHelper.py
bigdl/dllib/keras/__init__.py
bigdl/dllib/keras/autograd.py
bigdl/dllib/keras/base.py
bigdl/dllib/keras/converter.py
bigdl/dllib/keras/metrics.py
bigdl/dllib/keras/models.py
bigdl/dllib/keras/objectives.py
bigdl/dllib/keras/optimizers.py
bigdl/dllib/keras/regularizers.py
bigdl/dllib/keras/utils.py
bigdl/dllib/keras/datasets/__init__.py
bigdl/dllib/keras/datasets/boston_housing.py
bigdl/dllib/keras/datasets/imdb.py
bigdl/dllib/keras/datasets/mnist.py
bigdl/dllib/keras/datasets/reuters.py
bigdl/dllib/keras/engine/__init__.py
bigdl/dllib/keras/engine/topology.py
bigdl/dllib/keras/layers/__init__.py
bigdl/dllib/keras/layers/advanced_activations.py
bigdl_dllib_spark321-2.1.0b202207291.dist-info/METADATA
bigdl_dllib_spark321-2.1.0b202207291.dist-info/WHEEL
bigdl_dllib_spark321-2.1.0b202207291.dist-info/dependency_links.txt
bigdl_dllib_spark321-2.1.0b202207291.dist-info/top_level.txt
bigdl_dllib_spark321-2.1.0b202207291.dist-info/RECORD
