Metadata-Version: 2.1
Name: bigdl-dllib-spark321
Version: 2.1.0b202207291
Summary: Distributed Deep Learning Library for Apache Spark
Home-page: https://github.com/intel-analytics/BigDL
Author: BigDL Authors
Author-email: bigdl-user-group@googlegroups.com
License: Apache License, Version 2.0
Platform: mac
Platform: linux
Classifier: License :: OSI Approved :: Apache Software License
Classifier: Programming Language :: Python :: 3
Classifier: Programming Language :: Python :: 3.6
Classifier: Programming Language :: Python :: 3.7
Classifier: Programming Language :: Python :: Implementation :: CPython
Requires-Dist: numpy (>=1.19.5)
Requires-Dist: pyspark (==3.2.1)
Requires-Dist: conda-pack (==0.3.1)
Requires-Dist: six (>=1.10.0)
Requires-Dist: bigdl-core (==2.1.0b20220321)
